{
  "content_type": "Flashcard Maker",
  "section": "sub-unit-3",
  "generated_at": "2026-02-05T19:00:33.204616",
  "flashcards": {
    "questions": [
      {
        "question": "Who is Pranav M. Balasubramaniam from?",
        "correct_answer": "Palakkad in Kerala",
        "explanation": ""
      },
      {
        "question": "What are the challenges faced by Ila Sachani?",
        "correct_answer": "Born with hands hanging loose, unable to use her hands in the usual way",
        "explanation": ""
      },
      {
        "question": "How did Ila Sachani learn Kathiawar embroidery?",
        "correct_answer": "Using her feet",
        "explanation": ""
      },
      {
        "question": "What is special about Pranav M. Balasubramaniam?",
        "correct_answer": "Born without both hands, but excelled as an artist, singer, and para-sportsperson",
        "explanation": ""
      },
      {
        "question": "Where did Ila Sachani's mother and grandmother teach her Kathiawar embroidery?",
        "correct_answer": "The quiet settings of Amreli, Gujarat",
        "explanation": ""
      },
      {
        "question": "What is the name of the style of embroidery that Ila Sachani excels in?",
        "correct_answer": "Kathiawar embroidery",
        "explanation": ""
      },
      {
        "question": "Who helped Ila Sachani learn to do things with her legs?",
        "correct_answer": "Her parents and younger brother and sister",
        "explanation": ""
      },
      {
        "question": "What is the name of the exhibition where Ila Sachani's work was displayed?",
        "correct_answer": "State exhibition in Surat",
        "explanation": ""
      },
      {
        "question": "How did people react to Ila Sachani's embroidery skills?",
        "correct_answer": "Awestruck and admired her talent",
        "explanation": ""
      },
      {
        "question": "What is the result of Ila Sachani's hard work and determination?",
        "correct_answer": "Fame and recognition for her work",
        "explanation": ""
      }
    ],
    "notes": [
      {
        "title": "Pranav M. Balasubramaniam's Achievements",
        "content": "Excels as an artist, singer, and para-sportsperson despite being born without both hands"
      },
      {
        "title": "Ila Sachani's Challenges",
        "content": "Born with hands hanging loose, unable to use her hands in the usual way"
      },
      {
        "title": "Kathiawar Embroidery Style",
        "content": "Requires a lot of skill and is traditionally done using feet"
      },
      {
        "title": "Ila Sachani's Determination",
        "content": "She accepted the challenge of learning embroidery with her feet and became an expert at a young age"
      },
      {
        "title": "Pranav M. Balasubramaniam's Qualities",
        "content": "Important qualities for success include determination, hard work, and passion"
      },
      {
        "title": "Ila Sachani's Journey",
        "content": "From being born with a disability to becoming a famous embroiderer"
      },
      {
        "title": "Kathiawar Embroidery Importance",
        "content": "Preserves traditional art and culture of Gujarat"
      },
      {
        "title": "Ila Sachani's Support System",
        "content": "Her mother, grandmother, parents, and siblings supported her in learning embroidery"
      },
      {
        "title": "Pranav M. Balasubramaniam's Message",
        "content": "Perseverance and determination can overcome any challenge"
      },
      {
        "title": "Ila Sachani's Success",
        "content": "Her hard work and dedication led to fame, recognition, and financial stability"
      }
    ],
    "facts": [
      {
        "fact": "Pranav M. Balasubramaniam is from Palakkad in Kerala."
      },
      {
        "fact": "Ila Sachani was born with her hands hanging loose by her sides."
      },
      {
        "fact": "Kathiawar embroidery requires a lot of skill and is traditionally done using feet."
      },
      {
        "fact": "Pranav M. Balasubramaniam excels as an artist, singer, and para-sportsperson despite being born without both hands."
      },
      {
        "fact": "Ila Sachani's mother and grandmother taught her Kathiawar embroidery using her feet."
      },
      {
        "fact": "The government office in Surat displayed Ila Sachani's work at a state exhibition, leading to her fame."
      },
      {
        "fact": "Pranav M. Balasubramaniam's determination and hard work led to his success as an artist, singer, and para-sportsperson."
      },
      {
        "fact": "Ila Sachani's younger brother and sister helped her learn to do things with her legs."
      },
      {
        "fact": "Kathiawar embroidery is a traditional art form of Gujarat that requires a lot of skill and patience."
      },
      {
        "fact": "Pranav M. Balasubramaniam's story inspires people to persevere and overcome any challenge."
      }
    ]
  }
}