{
  "class": "Class 7",
  "subject": "English",
  "chapter_name": "Rani Abbakka",
  "lesson_level": "Easy",
  "total_periods": 6,
  "period_duration_minutes": "40-45",
  "overall_learning_objectives": [
    "Understand the life and achievements of Rani Abbakka",
    "Identify her qualities like bravery, intelligence, and leadership",
    "Recognize key events and challenges she faced",
    "Develop basic reading comprehension and vocabulary",
    "Learn about historical figures through storytelling",
    "Reflect on courage and problem-solving"
  ],
  "lesson_plan": [
    {
      "period": 1,
      "title": "Introduction to Rani Abbakka",
      "topics_covered": [
        "Who Rani Abbakka was",
        "The time and place of her rule",
        "Importance of bravery and leadership"
      ],
      "teaching_strategy": [
        "Class discussion on historical leaders",
        "Teacher introduces the story and setting",
        "Read first few paragraphs aloud"
      ],
      "student_activities": [
        "List qualities of Rani Abbakka",
        "Discuss what makes a leader brave"
      ],
      "assessment": ["Oral questioning", "Pair discussion"]
    },
    {
      "period": 2,
      "title": "Key Events in the Story",
      "topics_covered": [
        "Important battles and challenges",
        "Strategies used by Rani Abbakka",
        "Her victories and accomplishments"
      ],
      "teaching_strategy": [
        "Guided reading of main events",
        "Teacher explains historical context"
      ],
      "student_activities": [
        "Summarize main events in 3–4 sentences",
        "Highlight challenges Rani Abbakka faced"
      ],
      "assessment": ["Written summary", "Oral questioning"]
    },
    {
      "period": 3,
      "title": "Qualities and Leadership",
      "topics_covered": [
        "Bravery, intelligence, and strategic thinking",
        "Decision-making under pressure",
        "Impact on her kingdom and people"
      ],
      "teaching_strategy": [
        "Discussion of leadership qualities",
        "Teacher explains examples from the text"
      ],
      "student_activities": [
        "List examples of Rani Abbakka’s leadership",
        "Discuss in pairs which quality was most important"
      ],
      "assessment": ["List evaluation", "Class participation"]
    },
    {
      "period": 4,
      "title": "Reflection on Courage",
      "topics_covered": [
        "Personal courage in difficult situations",
        "Learning from historical examples",
        "Connecting to everyday life"
      ],
      "teaching_strategy": [
        "Class discussion on bravery",
        "Teacher encourages students to share reflections"
      ],
      "student_activities": [
        "Write a few sentences on one brave act of Rani Abbakka",
        "Share reflections with the class"
      ],
      "assessment": ["Written sentences", "Oral sharing"]
    },
    {
      "period": 5,
      "title": "Creative Activity",
      "topics_covered": [
        "Role-play of a historical scene",
        "Connecting story to imagination and expression"
      ],
      "teaching_strategy": [
        "Teacher explains scene to enact",
        "Students assign roles and act it out"
      ],
      "student_activities": [
        "Perform a short role-play showing Rani Abbakka’s courage",
        "Discuss feelings and decisions in the scene"
      ],
      "assessment": ["Participation and expression", "Understanding of events"]
    },
    {
      "period": 6,
      "title": "Vocabulary and Revision",
      "topics_covered": [
        "New words from the chapter",
        "Compound words and comprehension",
        "Short quiz on key events"
      ],
      "teaching_strategy": ["Worksheet exercises", "Revision quiz"],
      "student_activities": [
        "Use new words in sentences",
        "Answer comprehension questions",
        "Complete compound word exercises"
      ],
      "assessment": ["Worksheet completion", "Quiz evaluation"]
    }
  ],
  "teaching_aids": [
    "Textbook",
    "Whiteboard/Blackboard",
    "Chalk/Markers",
    "Printed timeline of Rani Abbakka",
    "Vocabulary worksheets"
  ],
  "evaluation_methods": [
    "Oral questioning",
    "Reading comprehension",
    "Role-play activity",
    "Paragraph writing",
    "Vocabulary exercises"
  ],
  "teacher_tip": "Encourage students to relate Rani Abbakka’s courage to challenges they face in daily life."
}