{
  "class": "Class 8",
  "subject": "Hindi",
  "chapter_name": "Patjhar Mein Tooti Pattiyan",
  "lesson_level": "Hard",
  "total_periods": 6,
  "period_duration_minutes": "40-45",
  "overall_learning_objectives": [
    "‘पतझर में टूटी पत्तियाँ’ पाठ के विचारों का विश्लेषण करना",
    "गिन्नी के सोने के उदाहरण के प्रतीकात्मक अर्थ को समझना",
    "आदर्श और व्यवहार के संबंध का आलोचनात्मक अध्ययन करना",
    "झेन दर्शन और टी-सेरेमनी के सांस्कृतिक और दार्शनिक महत्व को समझना",
    "पाठ के माध्यम से जीवन मूल्यों का विश्लेषण करना",
    "पाठ के विचारों को आधुनिक जीवन से जोड़कर समझना"
  ],
  "lesson_plan": [
    {
      "period": 1,
      "title": "पाठ और लेखक का गहन परिचय",
      "topics_covered": [
        "‘पतझर में टूटी पत्तियाँ’ पाठ का परिचय",
        "रवींद्र केलकर का साहित्यिक योगदान",
        "जीवन और समाज पर लेखक के विचार"
      ],
      "teaching_strategy": [
        "व्याख्या पद्धति",
        "प्रश्नोत्तर पद्धति",
        "समूह चर्चा"
      ],
      "student_activities": [
        "विद्यार्थी लेखक के विचारों पर चर्चा करें",
        "लेखक के विचारों को वर्तमान समाज से जोड़ें"
      ],
      "assessment": ["मौखिक प्रश्न", "कक्षा सहभागिता"]
    },
    {
      "period": 2,
      "title": "पाठ का वाचन और भाषा विश्लेषण",
      "topics_covered": [
        "पाठ का भावपूर्ण वाचन",
        "कठिन शब्दों और वाक्यों का अर्थ",
        "पाठ की भाषा और शैली"
      ],
      "teaching_strategy": [
        "सामूहिक वाचन",
        "शब्दार्थ व्याख्या",
        "भाषा विश्लेषण"
      ],
      "student_activities": [
        "विद्यार्थी कठिन शब्दों का अर्थ लिखें",
        "पाठ की भाषा शैली के उदाहरण खोजें"
      ],
      "assessment": ["कॉपी जाँच", "पाठ अभ्यास"]
    },
    {
      "period": 3,
      "title": "गिन्नी का सोना – प्रतीकात्मक अर्थ",
      "topics_covered": [
        "गिन्नी के सोने का उदाहरण",
        "प्रतीकात्मक अर्थ",
        "आदर्श और व्यवहार का संबंध"
      ],
      "teaching_strategy": ["उदाहरण आधारित व्याख्या", "विश्लेषणात्मक चर्चा"],
      "student_activities": [
        "गिन्नी के सोने का प्रतीकात्मक अर्थ लिखें",
        "आदर्श और व्यवहार की तुलना करें"
      ],
      "assessment": ["लिखित कार्य", "शिक्षक अवलोकन"]
    },
    {
      "period": 4,
      "title": "झेन दर्शन और जीवन दृष्टि",
      "topics_covered": [
        "झेन दर्शन का परिचय",
        "ध्यान और मानसिक शांति",
        "वर्तमान में जीने का महत्व"
      ],
      "teaching_strategy": ["समूह चर्चा", "व्याख्या पद्धति"],
      "student_activities": [
        "झेन दर्शन के विचारों पर चर्चा करें",
        "वर्तमान में जीने के लाभ लिखें"
      ],
      "assessment": ["समूह चर्चा", "लिखित उत्तर"]
    },
    {
      "period": 5,
      "title": "टी-सेरेमनी और सांस्कृतिक विश्लेषण",
      "topics_covered": [
        "टी-सेरेमनी की प्रक्रिया",
        "जापानी संस्कृति और दर्शन",
        "जीवन में सजगता और संतुलन"
      ],
      "teaching_strategy": ["चित्र आधारित व्याख्या", "तुलनात्मक चर्चा"],
      "student_activities": [
        "भारतीय और जापानी संस्कृति की तुलना करें",
        "टी-सेरेमनी के महत्व पर 5–6 वाक्य लिखें"
      ],
      "assessment": ["कॉपी जाँच", "मौखिक प्रश्न"]
    },
    {
      "period": 6,
      "title": "सार, विश्लेषण और मूल्यांकन",
      "topics_covered": [
        "पाठ के मुख्य विचारों की पुनरावृत्ति",
        "प्रतीक और उदाहरण",
        "पाठ का विश्लेषणात्मक सार"
      ],
      "teaching_strategy": [
        "क्विज",
        "पुनरावृत्ति चर्चा",
        "विश्लेषणात्मक प्रश्न"
      ],
      "student_activities": [
        "पाठ का विश्लेषणात्मक सार लिखें",
        "पाठ के विचारों को आधुनिक जीवन से जोड़ें"
      ],
      "assessment": ["लघु परीक्षण (10 अंक)", "संदेह समाधान"]
    }
  ],
  "teaching_aids": [
    "ब्लैकबोर्ड या व्हाइटबोर्ड",
    "चॉक या मार्कर",
    "हिंदी पाठ्यपुस्तक",
    "झेन दर्शन और टी-सेरेमनी से संबंधित चित्र"
  ],
  "evaluation_methods": [
    "मौखिक प्रश्न",
    "लिखित कार्य",
    "क्विज",
    "कक्षा चर्चा",
    "गतिविधियों में सहभागिता"
  ],
  "teacher_tip": "विद्यार्थियों को पाठ के उदाहरणों को अपने जीवन से जोड़कर समझाने के लिए प्रेरित करें ताकि वे आदर्श और व्यवहार के संतुलन को गहराई से समझ सकें।"
}
